AUTHORS
LICENSE
MANIFEST.in
README
setup.py
clean/__init__.py
clean/management/__init__.py
clean/management/commands/__init__.py
clean/management/commands/clean.py
django_clean.egg-info/PKG-INFO
django_clean.egg-info/SOURCES.txt
django_clean.egg-info/dependency_links.txt
django_clean.egg-info/top_level.txt
django_clean.egg-info/zip-safe