Metadata-Version: 1.0
Name: django-clean
Version: 0.1.2
Summary: Clean out files in a django app using regular expressions.
Home-page: http://github.com/ashchristopher/django-clean
Author: Ash Christopher
Author-email: ash.christopher@gmail.com
License: BSD
Download-URL: http://github.com/ashchristopher/django-clean/downloads
Keywords: django clean temporary cleanup pyc
Platform: UNKNOWN
Classifier: Development Status :: 5 - Production/Stable
Classifier: Environment :: Web Environment
Classifier: Intended Audience :: Developers
Classifier: License :: OSI Approved :: BSD License
Classifier: Operating System :: OS Independent
Classifier: Programming Language :: Python
Classifier: Framework :: Django
